LICENSE
MANIFEST.in
README.rst
pyproject.toml
setup.py
CyMySQL.egg-info/PKG-INFO
CyMySQL.egg-info/SOURCES.txt
CyMySQL.egg-info/dependency_links.txt
CyMySQL.egg-info/requires.txt
CyMySQL.egg-info/top_level.txt
cymysql/__init__.py
cymysql/__version__.py
cymysql/charset.pxd
cymysql/charset.py
cymysql/connections.py
cymysql/converters.py
cymysql/cursors.py
cymysql/err.py
cymysql/packet.py
cymysql/packet.pyx
cymysql/result.py
cymysql/result.pyx
cymysql/socketwrapper.py
cymysql/socketwrapper.pyx
cymysql/times.py
cymysql/aio/__init__.py
cymysql/aio/connections.py
cymysql/aio/context.py
cymysql/aio/cursors.py
cymysql/aio/pool.py
cymysql/aio/result.py
cymysql/aio/socketwrapper.py
cymysql/constants/CLIENT.py
cymysql/constants/COMMAND.py
cymysql/constants/CR.py
cymysql/constants/ER.py
cymysql/constants/FIELD_TYPE.py
cymysql/constants/FLAG.py
cymysql/constants/SERVER_STATUS.py
cymysql/constants/__init__.py
cymysql/tests/__init__.py
cymysql/tests/base.py
cymysql/tests/test_DictCursor.py
cymysql/tests/test_async.py
cymysql/tests/test_basic.py
cymysql/tests/test_example.py
cymysql/tests/test_issues.py