Metadata-Version: 2.4
Name: CyMySQL
Version: 1.1.1
Summary: Python MySQL Driver using Cython
Author-email: Yutaka Matsubara <yutaka.matsubara@gmail.com>
Maintainer-email: Hajime Nakagami <nakagami@gmail.com>
Project-URL: Project, https://github.com/nakagami/CyMySQL/
Keywords: MySQL
Classifier: Development Status :: 4 - Beta
Classifier: Operating System :: OS Independent
Classifier: Programming Language :: Python
Classifier: Programming Language :: Python :: 3
Classifier: Topic :: Database
Classifier: Topic :: Database :: Front-Ends
Classifier: Topic :: Software Development :: Libraries :: Python Modules
License-File: LICENSE
Requires-Dist: pycryptodome
Provides-Extra: zstd
Requires-Dist: pyzstd; extra == "zstd"
Provides-Extra: vector
Requires-Dist: numpy; extra == "vector"
Dynamic: license-file
